{"appleSKU":"com.Lunexis-Technologies.SuperThief","appleTeamID":"326D4S4RDH","enableCodelessAutoInitialization":false,"enableUnityGamingServicesAutoInitialization":true,"products":[{"id":"com.superthief.diamonds.starter","type":0,"storeIDs":[],"defaultDescription":{"googleLocale":4,"title":"100 Diamonds","description":"Heist Diamonds let you purchase cosmetics like skins, masks, and gadgets."},"screenshotPath":"","applePriceTier":1,"googlePrice":{"data":[99,0,0,131072],"num":0.99},"pricingTemplateID":"","descriptions":[],"udpPrice":{"data":[0,0,0,0],"num":0.0},"payouts":[{"t":"Currency","st":"Diamonds","q":100.0,"d":""}]},{"id":"com.superthief.diamonds.basic","type":0,"storeIDs":[],"defaultDescription":{"googleLocale":4,"title":"500 Diamonds","description":"Heist Diamonds let you purchase cosmetics like skins, masks, and gadgets."},"screenshotPath":"","applePriceTier":5,"googlePrice":{"data":[499,0,0,131072],"num":4.99},"pricingTemplateID":"","descriptions":[],"udpPrice":{"data":[0,0,0,0],"num":0.0},"payouts":[{"t":"Currency","st":"Diamonds","q":500.0,"d":""}]},{"id":"com.superthief.diamonds.advanced","type":0,"storeIDs":[],"defaultDescription":{"googleLocale":4,"title":"1200 Diamonds","description":"Heist Diamonds let you purchase cosmetics like skins, masks, and gadgets."},"screenshotPath":"","applePriceTier":10,"googlePrice":{"data":[999,0,0,131072],"num":9.99},"pricingTemplateID":"","descriptions":[],"udpPrice":{"data":[0,0,0,0],"num":0.0},"payouts":[{"t":"Currency","st":"Diamonds","q":1200.0,"d":""}]},{"id":"com.superthief.diamonds.pro","type":0,"storeIDs":[],"defaultDescription":{"googleLocale":4,"title":"2500 Diamonds","description":"Heist Diamonds let you purchase cosmetics like skins, masks, and gadgets."},"screenshotPath":"","applePriceTier":20,"googlePrice":{"data":[1999,0,0,131072],"num":19.99},"pricingTemplateID":"","descriptions":[],"udpPrice":{"data":[0,0,0,0],"num":0.0},"payouts":[{"t":"Currency","st":"Diamonds","q":2500.0,"d":""}]}]}